fswlib/__init__.py
fswlib/build.py
fswlib/test.py
fswlib/versions.py
fswlib/fsw_embedding/__init__.py
fswlib/fsw_embedding/build_fsw_embedding.py
fswlib/fsw_embedding/fsw_embedding.cu
fswlib/fsw_embedding/fsw_embedding.dll
fswlib/fsw_embedding/fsw_embedding.exp
fswlib/fsw_embedding/fsw_embedding.lib
fswlib/fsw_embedding/fsw_embedding.py
fswlib/fsw_embedding/libfsw_embedding.dylib
fswlib/fsw_embedding/libfsw_embedding.so
fswlib/fsw_embedding/test_fsw_embedding.py
fswlib-0.9.9.dist-info/licenses/LICENSE
fswlib-0.9.9.dist-info/METADATA
fswlib-0.9.9.dist-info/WHEEL
fswlib-0.9.9.dist-info/entry_points.txt
fswlib-0.9.9.dist-info/top_level.txt
fswlib-0.9.9.dist-info/RECORD
