Metadata-Version: 2.4
Name: fswlib
Version: 0.9.9
Summary: A PyTorch library for computing the Fourier Sliced-Wasserstein (FSW) embedding
Author-email: Tal Amir <talamir@technion.ac.il>, Nadav Dym <nadavdym@technion.ac.il>
Maintainer-email: Tal Amir <talamir@technion.ac.il>
License: BSD 3-Clause License
Project-URL: Homepage, https://github.com/tal-amir/fswlib
Project-URL: Repository, https://github.com/tal-amir/fswlib
Project-URL: Documentation, https://tal-amir.github.io/fswlib
Keywords: sliced Wasserstein,Fourier Sliced Wasserstein,FSW embedding,multiset embedding
Classifier: Development Status :: 4 - Beta
Classifier: Programming Language :: Python :: 3
Classifier: License :: OSI Approved :: BSD License
Classifier: Operating System :: OS Independent
Requires-Python: >=3.10.3
License-File: LICENSE
Requires-Dist: numpy>=1.24.4
Requires-Dist: torch>=2.1.0
Dynamic: license-file
